brian_lib/__init__.py
brian_lib/connectors/__init__.py
brian_lib/connectors/ftp.py
brian_lib/connectors/sharepoint.py
brian_lib/context_managers/__init__.py
brian_lib/context_managers/switch.py
brian_lib/decorators/__init__.py
brian_lib/decorators/general.py
brian_lib/decorators/logging_decorator.py
brian_lib/decorators/retry_decorator.py
brian_lib/utilities/__init__.py
brian_lib/utilities/data_transform.py
brian_lib/utilities/date_time.py
brian_lib/utilities/demography.py
brian_lib/utilities/downloader.py
brian_lib/utilities/file_management.py
brian_lib/utilities/rut.py
brian_lib/utilities/serialization.py
brian_lib/utilities/validation.py
brian_lib-0.2.6.dist-info/METADATA
brian_lib-0.2.6.dist-info/WHEEL
brian_lib-0.2.6.dist-info/top_level.txt
brian_lib-0.2.6.dist-info/RECORD
