Metadata-Version: 2.1
Name: brian-lib
Version: 0.2.6
Summary: UNKNOWN
Home-page: UNKNOWN
Author: Brain Food
License: MIT
Platform: UNKNOWN
Requires-Python: >=3.9
Requires-Dist: pandas ==2.1.3
Requires-Dist: beartype ==0.16.4
Requires-Dist: urllib3 ==1.26.15
Requires-Dist: requests-toolbelt ==0.10.1
Requires-Dist: pyarrow ==14.0.1
Requires-Dist: openpyxl ==3.1.2
Requires-Dist: python-dotenv ==0.19.2
Requires-Dist: SQLAlchemy ==1.4.32
Requires-Dist: PyMySQL ==1.1.0
Requires-Dist: PyGreSQL ==6.0
Requires-Dist: azure-storage-blob ==12.19.0
Requires-Dist: ephem ==4.1.5
Requires-Dist: loguru ==0.7.2
Requires-Dist: SharePlum ==0.5.1
